pygraft/__init__.py
pygraft/class_generator.py
pygraft/kg_generator.py
pygraft/main.py
pygraft/pygraft.py
pygraft/relation_generator.py
pygraft/schema_constructor.py
pygraft/utils.py
pygraft/utils_kg.py
pygraft/utils_schema.py
pygraft/examples/template.json
pygraft/examples/template.yml
pygraft/property_checks/combinations.json
pygraft/property_checks/compat_p1p2_inverseof.txt
pygraft-0.0.3.dist-info/LICENSE.txt
pygraft-0.0.3.dist-info/METADATA
pygraft-0.0.3.dist-info/WHEEL
pygraft-0.0.3.dist-info/entry_points.txt
pygraft-0.0.3.dist-info/top_level.txt
pygraft-0.0.3.dist-info/RECORD
