Metadata-Version: 2.1
Name: pygraft
Version: 0.0.3
Summary: PyGraft: Configurable Generation of Schemas and Knowledge Graphs at Your Fingertips
Home-page: https://github.com/nicolas-hbt
Author: Nicolas Hubert
Author-email: Nicolas Hubert <nicolas.hubert@univ-lorraine.fr>
License: MIT
Keywords: Knowledge Graph,Ontology,Schema,Semantic Web,Synthetic Data Generator
Classifier: Development Status :: 4 - Beta
Classifier: Intended Audience :: Science/Research
Classifier: Topic :: Software Development :: Build Tools
Classifier: License :: OSI Approved :: MIT License
Classifier: Programming Language :: Python :: 3 :: Only
Classifier: Programming Language :: Python :: 3.7
Classifier: Programming Language :: Python :: 3.8
Classifier: Programming Language :: Python :: 3.9
Classifier: Programming Language :: Python :: 3.10
Classifier: Programming Language :: Python :: 3.11
Classifier: Topic :: Scientific/Engineering :: Artificial Intelligence
Classifier: Topic :: Scientific/Engineering :: Information Analysis
Requires-Python: >=3.7
License-File: LICENSE.txt
Requires-Dist: numpy (>=1.24.0)
Requires-Dist: matplotlib (>=3.7.0)
Requires-Dist: Owlready2 (>=0.41)
Requires-Dist: rdflib (>=6.2.0)
Requires-Dist: pyyaml
Requires-Dist: tabulate
Requires-Dist: art
Requires-Dist: tqdm
